[
    {
        "productId": 88192024,
        "productName": "미프 미남크림 썬 비비 남성용 비비크림 SPF50+ PA+++ 50ml, 1개",
        "productPrice": 20900,
        "productImage": "https://static.coupangcdn.com/image/retail/images/11326461464460424-8600b629-957e-4a5f-b186-434b511903fb.jpg",
        "productUrl": "https://link.coupang.com/re/AFFSDP?lptag=AF8104485&subid=eungwang1203&pageKey=88192024&itemId=276153110&vendorItemId=3669875678&traceid=V0-153-901dcbd3199ae225",
        "keyword": "남자BB크림",
        "rank": 1,
        "isRocket": true,
        "isFreeShipping": false
    },
    {
        "productId": 81597794,
        "productName": "다슈 맨즈 아쿠아 톤업 비비로션 40ml, 23호, 1개",
        "productPrice": 13600,
        "productImage": "https://static.coupangcdn.com/image/retail/images/6510232608237741-3b505aa3-db58-4935-bece-9ec08e87a5e4.jpg",
        "productUrl": "https://link.coupang.com/re/AFFSDP?lptag=AF8104485&subid=eungwang1203&pageKey=81597794&itemId=260018720&vendorItemId=3631673451&traceid=V0-153-f735fdc99f95e4a2",
        "keyword": "남자BB크림",
        "rank": 2,
        "isRocket": true,
        "isFreeShipping": false
    },
    {
        "productId": 4730662719,
        "productName": "폴메디슨 옴므 올인원 비비크림 60ml SPF 50 PA+++, 1개",
        "productPrice": 9390,
        "productImage": "https://static.coupangcdn.com/image/retail/images/774061538251100-5912272a-decc-48fa-922c-69a89119dd81.jpg",
        "productUrl": "https://link.coupang.com/re/AFFSDP?lptag=AF8104485&subid=eungwang1203&pageKey=4730662719&itemId=5994909461&vendorItemId=73292704042&traceid=V0-153-23c3e8005efd87da",
        "keyword": "남자BB크림",
        "rank": 3,
        "isRocket": true,
        "isFreeShipping": false
    },
    {
        "productId": 88192024,
        "productName": "미프 미남크림 썬 비비 남성용 비비크림 SPF50+ PA+++ 50ml, 1개",
        "productPrice": 20900,
        "productImage": "https://static.coupangcdn.com/image/retail/images/11326461464460424-8600b629-957e-4a5f-b186-434b511903fb.jpg",
        "productUrl": "https://link.coupang.com/re/AFFSDP?lptag=AF8104485&subid=eungwang1203&pageKey=88192024&itemId=276153110&vendorItemId=3669875678&traceid=V0-153-901dcbd3199ae225",
        "keyword": "남자BB크림",
        "rank": 4,
        "isRocket": true,
        "isFreeShipping": false
    },
    {
        "productId": 6006517688,
        "productName": "[오브제] 내추럴 커버 파운데이션 스틱 남성파운데이션 커버스틱, 2호 베이지",
        "productPrice": 36800,
        "productImage": "https://static.coupangcdn.com/image/vendor_inventory/655f/22ade0f7efbb3125fea55a6e479483d2998dd776130c1411a880088437ab.jpg",
        "productUrl": "https://link.coupang.com/re/AFFSDP?lptag=AF8104485&subid=eungwang1203&pageKey=6006517688&itemId=10886886390&vendorItemId=78166764935&traceid=V0-153-ad617909fc2dfbea",
        "keyword": "남자BB크림",
        "rank": 5,
        "isRocket": false,
        "isFreeShipping": false
    },
    {
        "productId": 6075317069,
        "productName": "랩시리즈 BB 틴티드 모이스춰라이저 50ml, 1개",
        "productPrice": 52330,
        "productImage": "https://static.coupangcdn.com/image/retail/images/2021/09/10/13/3/da8697fd-d9dd-4de0-8194-f32372a6762c.jpg",
        "productUrl": "https://link.coupang.com/re/AFFSDP?lptag=AF8104485&subid=eungwang1203&pageKey=6075317069&itemId=11235249648&vendorItemId=78512542263&traceid=V0-153-1bf10f70dcee88e3",
        "keyword": "남자BB크림",
        "rank": 6,
        "isRocket": true,
        "isFreeShipping": false
    },
    {
        "productId": 81597794,
        "productName": "다슈 맨즈 아쿠아 톤업 비비로션 40ml, 23호, 2개",
        "productPrice": 27200,
        "productImage": "https://static.coupangcdn.com/image/retail/images/6510234232684388-af04179d-6ee8-4562-8d40-9e36cb9455be.jpg",
        "productUrl": "https://link.coupang.com/re/AFFSDP?lptag=AF8104485&subid=eungwang1203&pageKey=81597794&itemId=2487979476&vendorItemId=70481221059&traceid=V0-153-f735fdc99f95e4a2",
        "keyword": "남자BB크림",
        "rank": 7,
        "isRocket": true,
        "isFreeShipping": false
    },
    {
        "productId": 4730662719,
        "productName": "폴메디슨 옴므 올인원 비비크림 60ml SPF 50 PA+++, 2개",
        "productPrice": 18680,
        "productImage": "https://static.coupangcdn.com/image/retail/images/1784955793123315-00ca1698-ceb2-4d9c-9375-b4b466acb5dd.jpg",
        "productUrl": "https://link.coupang.com/re/AFFSDP?lptag=AF8104485&subid=eungwang1203&pageKey=4730662719&itemId=5994909455&vendorItemId=73292704016&traceid=V0-153-23c3e8005efd87da",
        "keyword": "남자BB크림",
        "rank": 8,
        "isRocket": true,
        "isFreeShipping": false
    },
    {
        "productId": 4730662719,
        "productName": "폴메디슨 옴므 올인원 비비크림 60ml SPF 50 PA+++, 1개",
        "productPrice": 9390,
        "productImage": "https://static.coupangcdn.com/image/retail/images/774061538251100-5912272a-decc-48fa-922c-69a89119dd81.jpg",
        "productUrl": "https://link.coupang.com/re/AFFSDP?lptag=AF8104485&subid=eungwang1203&pageKey=4730662719&itemId=5994909461&vendorItemId=73292704042&traceid=V0-153-23c3e8005efd87da",
        "keyword": "남자BB크림",
        "rank": 9,
        "isRocket": true,
        "isFreeShipping": false
    },
    {
        "productId": 6102049550,
        "productName": "다슈 맨즈 아쿠아 매트 비비 쿠션 15g, 딥베이지, 1개",
        "productPrice": 16800,
        "productImage": "https://static.coupangcdn.com/image/retail/images/1137666255013839-5cb7bb1b-985e-42d6-9bb6-d468dae0914c.jpg",
        "productUrl": "https://link.coupang.com/re/AFFSDP?lptag=AF8104485&subid=eungwang1203&pageKey=6102049550&itemId=11441301743&vendorItemId=5510428756&traceid=V0-153-e82b28bdd8a994ea",
        "keyword": "남자BB크림",
        "rank": 10,
        "isRocket": true,
        "isFreeShipping": false
    }
]