[
    {
        "productId": 6102049550,
        "productName": "다슈 맨즈 아쿠아 매트 비비 쿠션 15g, 딥베이지, 1개",
        "productPrice": 16800,
        "productImage": "https://static.coupangcdn.com/image/retail/images/1137666255013839-5cb7bb1b-985e-42d6-9bb6-d468dae0914c.jpg",
        "productUrl": "https://link.coupang.com/re/AFFSDP?lptag=AF8104485&subid=eungwang1203&pageKey=6102049550&itemId=11441301743&vendorItemId=5510428756&traceid=V0-153-e82b28bdd8a994ea",
        "keyword": "남자쿠션",
        "rank": 1,
        "isRocket": true,
        "isFreeShipping": false
    },
    {
        "productId": 6102049550,
        "productName": "다슈 맨즈 아쿠아 매트 비비 쿠션 15g, 딥베이지, 1개",
        "productPrice": 16800,
        "productImage": "https://static.coupangcdn.com/image/retail/images/1137666255013839-5cb7bb1b-985e-42d6-9bb6-d468dae0914c.jpg",
        "productUrl": "https://link.coupang.com/re/AFFSDP?lptag=AF8104485&subid=eungwang1203&pageKey=6102049550&itemId=11441301743&vendorItemId=5510428756&traceid=V0-153-e82b28bdd8a994ea",
        "keyword": "남자쿠션",
        "rank": 2,
        "isRocket": true,
        "isFreeShipping": false
    },
    {
        "productId": 5334581082,
        "productName": "아이오페 맨 에어쿠션 16g, 01호 라이트베이지, 1개",
        "productPrice": 14870,
        "productImage": "https://static.coupangcdn.com/image/retail/images/87074374012515-07ea413a-761d-4dd6-9b73-ccbf78adda29.png",
        "productUrl": "https://link.coupang.com/re/AFFSDP?lptag=AF8104485&subid=eungwang1203&pageKey=5334581082&itemId=7796419330&vendorItemId=75086419199&traceid=V0-153-4b4bf54cb277186a",
        "keyword": "남자쿠션",
        "rank": 3,
        "isRocket": true,
        "isFreeShipping": false
    },
    {
        "productId": 5165909631,
        "productName": "비레디 마그네틱 피팅 쿠션 포 히어로즈 15g, 3호 제프리, 1개",
        "productPrice": 15880,
        "productImage": "https://static.coupangcdn.com/image/retail/images/155224435335424-b7ed7df6-a8e8-4255-909d-5924e1bd8d49.png",
        "productUrl": "https://link.coupang.com/re/AFFSDP?lptag=AF8104485&subid=eungwang1203&pageKey=5165909631&itemId=7072752733&vendorItemId=74364861948&traceid=V0-153-b966463e404194bd",
        "keyword": "남자쿠션",
        "rank": 4,
        "isRocket": true,
        "isFreeShipping": false
    },
    {
        "productId": 6006517688,
        "productName": "[오브제] 내추럴 커버 파운데이션 스틱 남성파운데이션 커버스틱, 1호 아이보리",
        "productPrice": 36800,
        "productImage": "https://static.coupangcdn.com/image/vendor_inventory/655f/22ade0f7efbb3125fea55a6e479483d2998dd776130c1411a880088437ab.jpg",
        "productUrl": "https://link.coupang.com/re/AFFSDP?lptag=AF8104485&subid=eungwang1203&pageKey=6006517688&itemId=10886886380&vendorItemId=78166764925&traceid=V0-153-ad617909fc2dfbea",
        "keyword": "남자쿠션",
        "rank": 5,
        "isRocket": false,
        "isFreeShipping": false
    },
    {
        "productId": 5334581082,
        "productName": "아이오페 맨 에어쿠션 16g, 01호 라이트베이지, 1개",
        "productPrice": 14870,
        "productImage": "https://static.coupangcdn.com/image/retail/images/87074374012515-07ea413a-761d-4dd6-9b73-ccbf78adda29.png",
        "productUrl": "https://link.coupang.com/re/AFFSDP?lptag=AF8104485&subid=eungwang1203&pageKey=5334581082&itemId=7796419330&vendorItemId=75086419199&traceid=V0-153-4b4bf54cb277186a",
        "keyword": "남자쿠션",
        "rank": 6,
        "isRocket": true,
        "isFreeShipping": false
    },
    {
        "productId": 5334581082,
        "productName": "아이오페 맨 에어쿠션 16g, 02호 내추럴베이지, 1개",
        "productPrice": 14870,
        "productImage": "https://static.coupangcdn.com/image/retail/images/87056226025939-d298c48d-e628-44b0-aed8-16d1c14fa96c.png",
        "productUrl": "https://link.coupang.com/re/AFFSDP?lptag=AF8104485&subid=eungwang1203&pageKey=5334581082&itemId=7796419332&vendorItemId=75086419213&traceid=V0-153-4b4bf54cb277186a",
        "keyword": "남자쿠션",
        "rank": 7,
        "isRocket": true,
        "isFreeShipping": false
    },
    {
        "productId": 327987518,
        "productName": "그라펜 남성용 핸섬 커버 쿠션 15g, 3호, 1개",
        "productPrice": 20490,
        "productImage": "https://static.coupangcdn.com/image/retail/images/24291057497441-4498011e-4006-4edc-bfe1-755cec6c8091.jpg",
        "productUrl": "https://link.coupang.com/re/AFFSDP?lptag=AF8104485&subid=eungwang1203&pageKey=327987518&itemId=1049155453&vendorItemId=5514191835&traceid=V0-153-b68690a03d99cf9c",
        "keyword": "남자쿠션",
        "rank": 8,
        "isRocket": true,
        "isFreeShipping": false
    },
    {
        "productId": 5165909631,
        "productName": "비레디 마그네틱 피팅 쿠션 포 히어로즈 15g, 3호 제프리, 1개",
        "productPrice": 15880,
        "productImage": "https://static.coupangcdn.com/image/retail/images/155224435335424-b7ed7df6-a8e8-4255-909d-5924e1bd8d49.png",
        "productUrl": "https://link.coupang.com/re/AFFSDP?lptag=AF8104485&subid=eungwang1203&pageKey=5165909631&itemId=7072752733&vendorItemId=74364861948&traceid=V0-153-b966463e404194bd",
        "keyword": "남자쿠션",
        "rank": 9,
        "isRocket": true,
        "isFreeShipping": false
    },
    {
        "productId": 327987518,
        "productName": "그라펜 남성용 핸섬 커버 쿠션 15g, 1호, 1개",
        "productPrice": 20490,
        "productImage": "https://static.coupangcdn.com/image/retail/images/27184133258920-f1b7f568-cd49-4f43-91c8-e74e2306c781.jpg",
        "productUrl": "https://link.coupang.com/re/AFFSDP?lptag=AF8104485&subid=eungwang1203&pageKey=327987518&itemId=1049155441&vendorItemId=5514191816&traceid=V0-153-b68690a03d99cf9c",
        "keyword": "남자쿠션",
        "rank": 10,
        "isRocket": true,
        "isFreeShipping": false
    }
]